rxconf/__init__.py
rxconf/_types.py
rxconf/attributes.py
rxconf/config_builder.py
rxconf/config_resolver.py
rxconf/config_types.py
rxconf/exceptions.py
rxconf/hashtools.py
rxconf/rxconf.py
rxconf-0.0.5.1.dist-info/LICENSE
rxconf-0.0.5.1.dist-info/METADATA
rxconf-0.0.5.1.dist-info/WHEEL
rxconf-0.0.5.1.dist-info/RECORD
