Metadata-Version: 2.3
Name: rxconf
Version: 0.0.5.1
Summary: Powerful and flexible library for realtime configuration management in Python
License: MIT
Keywords: configuration,settings,yaml,json,toml,ini,env
Author: Andrey Karchevsky
Author-email: karych@karych.ru
Requires-Python: >=3.9,<4.0
Classifier: License :: OSI Approved :: MIT License
Classifier: Operating System :: OS Independent
Classifier: Programming Language :: Python :: 3
Classifier: Programming Language :: Python :: 3.9
Classifier: Programming Language :: Python :: 3.10
Classifier: Programming Language :: Python :: 3.11
Classifier: Programming Language :: Python :: 3.12
Classifier: Programming Language :: Python :: 3.13
Classifier: Topic :: Software Development
Classifier: Topic :: Software Development :: Libraries
Classifier: Topic :: Software Development :: Libraries :: Python Modules
Classifier: Topic :: Utilities
Requires-Dist: aiofiles (>=24.1.0,<25.0.0)
Requires-Dist: hvac (>=2.3.0,<3.0.0)
Requires-Dist: python-dotenv (>=1.0.1,<2.0.0)
Requires-Dist: pyyaml (>=6.0.2,<7.0.0)
Requires-Dist: toml (>=0.10.2,<0.11.0) ; python_version < "3.11"
Project-URL: Documentation, https://realkarych.github.io/rxconf/
Project-URL: Homepage, https://github.com/realkarych/rxconf/
Project-URL: Repository, https://github.com/realkarych/rxconf/
